LICENSE
MANIFEST.in
README.rst
requirements.txt
setup.py
p7doi/__init__.py
p7doi.egg-info/PKG-INFO
p7doi.egg-info/SOURCES.txt
p7doi.egg-info/dependency_links.txt
p7doi.egg-info/entry_points.txt
p7doi.egg-info/top_level.txt