Metadata-Version: 1.1
Name: p7doi
Version: 0.0.1
Summary: Read research papers through Paris 7's proxy
Home-page: https://github.com/bfontaine/p7doi
Author: Baptiste Fontaine
Author-email: b@ptistefontaine.fr
License: Copyright © 2014 – Baptiste Fontaine
